{
  "paper_index": 4,
  "paper_total": 92,
  "paper_title": "13-SmartDIMM- In-Memory Acceleration of Upper Layer Protocols.pdf",
  "started_at": "2026-05-15T17:47:15.269829",
  "ended_at": "2026-05-15T17:56:32.902513",
  "returncode": 0,
  "log_file": "/data3/paper_analysis/outputs/logs/004__13-SmartDIMM-_In-Memory_Acceleration_of_Upper_Layer_Protocols.pdf.stream.jsonl",
  "status_block": {
    "status_block_found": true,
    "raw_status_block": "paper_index: 4\npaper_total: 92\npaper_title: 13-SmartDIMM- In-Memory Acceleration of Upper Layer Protocols.pdf\npaper-experiment-idea: DONE\npaper-knowledge: DONE\noverall: DONE",
    "paper_index": "4",
    "paper_total": "92",
    "paper_title": "13-SmartDIMM- In-Memory Acceleration of Upper Layer Protocols.pdf",
    "paper-experiment-idea": "DONE",
    "paper-knowledge": "DONE",
    "overall": "DONE"
  },
  "process_status": "DONE"
}