{
  "paper_index": 60,
  "paper_total": 92,
  "paper_title": "62-SCAR- Scheduling Multi-Model AI Workloads on Heterogeneous Multi-Chiplet Module Accelereators.pdf",
  "started_at": "2026-05-16T07:42:41.400051",
  "ended_at": "2026-05-16T07:59:12.236579",
  "returncode": 0,
  "log_file": "/data3/paper_analysis/outputs/logs/060__62-SCAR-_Scheduling_Multi-Model_AI_Workloads_on_Heterogeneous_Multi-Chiplet_Module_Acceler.stream.jsonl",
  "status_block": {
    "status_block_found": true,
    "raw_status_block": "paper_index: 60\npaper_total: 92\npaper_title: 62-SCAR- Scheduling Multi-Model AI Workloads on Heterogeneous Multi-Chiplet Module Accelereators.pdf\npaper-experiment-idea: DONE\npaper-knowledge: DONE\noverall: DONE",
    "paper_index": "60",
    "paper_total": "92",
    "paper_title": "62-SCAR- Scheduling Multi-Model AI Workloads on Heterogeneous Multi-Chiplet Module Accelereators.pdf",
    "paper-experiment-idea": "DONE",
    "paper-knowledge": "DONE",
    "overall": "DONE"
  },
  "process_status": "DONE"
}