{
  "paper_index": 75,
  "paper_total": 100,
  "paper_title": "- **MagiCache**: A Virtual In-Cache Computing Engine",
  "started_at": "2026-05-15T12:28:14.420878",
  "ended_at": "2026-05-15T12:44:32.708856",
  "returncode": 0,
  "log_file": "/data3/paper_analysis/outputs/logs/075__-_MagiCache_A_Virtual_In-Cache_Computing_Engine.stream.jsonl",
  "status_block": {
    "status_block_found": true,
    "raw_status_block": "paper_index: 75\npaper_total: 100\npaper_title: - **MagiCache**: A Virtual In-Cache Computing Engine\npaper-experiment-idea: DONE\npaper-knowledge: DONE\noverall: DONE",
    "paper_index": "75",
    "paper_total": "100",
    "paper_title": "- **MagiCache**: A Virtual In-Cache Computing Engine",
    "paper-experiment-idea": "DONE",
    "paper-knowledge": "DONE",
    "overall": "DONE"
  },
  "process_status": "DONE"
}